epytope/__init__.py
epytope/CleavagePrediction/External.py
epytope/CleavagePrediction/PSSM.py
epytope/CleavagePrediction/__init__.py
epytope/Core/Allele.py
epytope/Core/Base.py
epytope/Core/Generator.py
epytope/Core/Peptide.py
epytope/Core/Protein.py
epytope/Core/Result.py
epytope/Core/Transcript.py
epytope/Core/Variant.py
epytope/Core/__init__.py
epytope/Data/DistanceMatrices.py
epytope/Data/__init__.py
epytope/Data/examples/Homo_sapiens.GRCh38.cds.test_stub.fa
epytope/Data/examples/Homo_sapiens.GRCh38.pep.test_stub.fa
epytope/Data/examples/__init__.py
epytope/Data/examples/alleles.txt
epytope/Data/examples/alleles_defect.txt
epytope/Data/examples/testSequences.fasta
epytope/Data/examples/testSequences_d2s.fasta
epytope/Data/examples/test_annovar.out
epytope/Data/examples/vcftestfile1.vcf
epytope/Data/examples/vcftestfile2.vcf
epytope/Data/examples/vcftestfile3.vcf
epytope/Data/pssms/__init__.py
epytope/Data/pssms/arb/__init__.py
epytope/Data/pssms/arb/mat/A_0101_10.py
epytope/Data/pssms/arb/mat/A_0101_9.py
epytope/Data/pssms/arb/mat/A_0201_10.py
epytope/Data/pssms/arb/mat/A_0201_11.py
epytope/Data/pssms/arb/mat/A_0201_8.py
epytope/Data/pssms/arb/mat/A_0201_9.py
epytope/Data/pssms/arb/mat/A_0202_10.py
epytope/Data/pssms/arb/mat/A_0202_11.py
epytope/Data/pssms/arb/mat/A_0202_8.py
epytope/Data/pssms/arb/mat/A_0202_9.py
epytope/Data/pssms/arb/mat/A_0203_10.py
epytope/Data/pssms/arb/mat/A_0203_11.py
epytope/Data/pssms/arb/mat/A_0203_8.py
epytope/Data/pssms/arb/mat/A_0203_9.py
epytope/Data/pssms/arb/mat/A_0206_10.py
epytope/Data/pssms/arb/mat/A_0206_11.py
epytope/Data/pssms/arb/mat/A_0206_8.py
epytope/Data/pssms/arb/mat/A_0206_9.py
epytope/Data/pssms/arb/mat/A_0211_9.py
epytope/Data/pssms/arb/mat/A_0212_9.py
epytope/Data/pssms/arb/mat/A_0216_9.py
epytope/Data/pssms/arb/mat/A_0219_9.py
epytope/Data/pssms/arb/mat/A_0250_9.py
epytope/Data/pssms/arb/mat/A_0301_10.py
epytope/Data/pssms/arb/mat/A_0301_9.py
epytope/Data/pssms/arb/mat/A_1101_10.py
epytope-3.4.0.dist-info/LICENSE.txt
epytope-3.4.0.dist-info/METADATA
epytope-3.4.0.dist-info/WHEEL
epytope-3.4.0.dist-info/top_level.txt
epytope-3.4.0.dist-info/RECORD
