Metadata-Version: 2.1
Name: epytope
Version: 3.4.0
Summary: A Framework for Epitope Detection and Vaccine Design
Home-page: https://github.com/KohlbacherLab/epytope
Author: Benjamin Schubert, Mathias Walzer, Christopher Mohr, Leon Kuchenbecker
Author-email: benjamin.schubert@helmholtz-muenchen.de, walzer@ebi.ac.uk, contact.cmohr@gmail.com, leon.kuchenbecker@uni-tuebingen.de 
Maintainer: Christopher Mohr, Jonas Scheid
Maintainer-email: contact.cmohr@gmail.com, jonas.scheid@uni-tuebingen.de
License: BSD
Keywords: epitope prediction vaccine design HLA MHC
Classifier: Development Status :: 5 - Production/Stable
Classifier: Intended Audience :: Science/Research
Classifier: Topic :: Scientific/Engineering :: Medical Science Apps.
Classifier: License :: OSI Approved :: BSD License
Classifier: Programming Language :: Python :: 3 :: Only
License-File: LICENSE.txt
Requires-Dist: setuptools
Requires-Dist: pandas >=1.3.5
Requires-Dist: pyomo >=4.0
Requires-Dist: PyMySQL
Requires-Dist: biopython
Requires-Dist: PyVCF3
Requires-Dist: mhcflurry <=1.4.3
Requires-Dist: mhcnuggets ==2.3.2
Requires-Dist: keras <=2.3.1
Requires-Dist: h5py <=2.10.0
Requires-Dist: requests
Requires-Dist: beautifulsoup4
